src/__init__.py
src/main.py
poc_python_cf_smvers-1.1.1.dist-info/METADATA
poc_python_cf_smvers-1.1.1.dist-info/WHEEL
poc_python_cf_smvers-1.1.1.dist-info/top_level.txt
poc_python_cf_smvers-1.1.1.dist-info/RECORD
