Metadata-Version: 2.4
Name: poc-python-cf-smvers
Version: 1.1.1
Summary: A simple Python Cloud Function with versioning
Author: MitVo
Author-email:  
Dynamic: author
Dynamic: author-email
Dynamic: summary
